sesum/LICENSE.md
sesum/README.md
sesum/__init__.py
sesum/sr.py
sesum/Licenses/LICENSE-Boost.txt
sesum/Licenses/LICENSE-KaHyPar.txt
sesum/Licenses/LICENSE-OpenBLAS.txt
sesum/Licenses/LICENSE-Sesum.txt
sesum/Licenses/LICENSE-highway.txt
sesum/Licenses/LICENSE-hptt.txt
sesum/Licenses/LICENSE-mimalloc.txt
sesum/Licenses/LICENSE-py-cpuinfo.txt
sesum/linux_arm64/libsr.so
sesum/linux_avx2/libsr.so
sesum/linux_avx512/libsr.so
sesum/mac_arm64/libsr.dylib
sesum/mac_avx2/libsr.dylib
sesum/src/src.zip
sesum/windows_arm64/libomp.dll
sesum/windows_arm64/libsr.dll
sesum/windows_avx2/libsr.dll
sesum/windows_avx512/libsr.dll
sesum-0.3.9.dist-info/METADATA
sesum-0.3.9.dist-info/WHEEL
sesum-0.3.9.dist-info/top_level.txt
sesum-0.3.9.dist-info/RECORD
