Metadata-Version: 2.1
Name: sesum
Version: 0.3.9
Summary: Scalable einsum with optimized path computation and efficient execution of large, complex tensor expressions
Author: Mark Blacher
License: GPL-3.0
Classifier: License :: OSI Approved :: GNU General Public License v3 (GPLv3)
Classifier: Programming Language :: Python :: 3
Requires-Dist: numpy
